CHANGELOG.md
LICENSE
MANIFEST.in
README.md
setup.py
stargazers/__init__.py
stargazers/align.py
stargazers/colors.py
stargazers/denoise.py
stargazers/edit.py
stargazers/flow.py
stargazers/gifs.py
stargazers/gradients.py
stargazers/io.py
stargazers/sle.py
stargazers/transform.py
stargazers/vfx.py
stargazers/video.py
stargazers.egg-info/PKG-INFO
stargazers.egg-info/SOURCES.txt
stargazers.egg-info/dependency_links.txt
stargazers.egg-info/requires.txt
stargazers.egg-info/top_level.txt
stargazers/mission/__init__.py
stargazers/mission/juno.py