Metadata-Version: 1.2
Name: stargazers
Version: 0.1.1.43
Summary: astronomical image processing in python
Home-page: UNKNOWN
Author: Bruno Constanzo
Author-email: bconstanzo@ufasta.edu.ar
License: LGPL 2.1
Platform: UNKNOWN
Requires-Python: >=3.6
